{
    "metadata": {
        "title": "Household item names in English with pictures",
        "bannerImage": "./assets/images/thumbnail/household-items.png",
        "createdAt": "1746331547023",
        "subtitle": "Household items names :",
        "description": "Armchair, Bed, Sofa, Table, Chair, Bookshelf, Mirror, Blanket, Umbrella, Clock, Broom, Scissors, Flashlight, Hammer, Basket, Teapot, and more."
    },
    "vocabularyList": [
        {
            "word": "Bed",
            "imagePath": "./assets/images/vocabulary/household-items/bed.png",
            "exampleSentence": "She lay down on the bed to rest."
        },
        {
            "word": "Sofa",
            "imagePath": "./assets/images/vocabulary/household-items/sofa.png",
            "exampleSentence": "They sat on the sofa and watched a movie."
        },
        {
            "word": "Table",
            "imagePath": "./assets/images/vocabulary/household-items/table.png",
            "exampleSentence": "We had dinner at the dining table."
        },
        {
            "word": "Chair",
            "imagePath": "./assets/images/vocabulary/household-items/chair.png",
            "exampleSentence": "He pulled out a chair and sat down."
        },
        {
            "word": "Armchair",
            "imagePath": "./assets/images/vocabulary/household-items/armchair.png",
            "exampleSentence": "Grandpa loves reading in his armchair."
        },
        {
            "word": "Television",
            "imagePath": "./assets/images/vocabulary/household-items/television.png",
            "exampleSentence": "The children watched cartoons on television."
        },
        {
            "word": "Lamp",
            "imagePath": "./assets/images/vocabulary/household-items/lamp.png",
            "exampleSentence": "She turned on the lamp to read a book."
        },
        {
            "word": "Bookshelf",
            "imagePath": "./assets/images/vocabulary/household-items/bookshelf.png",
            "exampleSentence": "The bookshelf was full of interesting books."
        },
        {
            "word": "Curtains",
            "imagePath": "./assets/images/vocabulary/household-items/curtains.png",
            "exampleSentence": "She opened the curtains to let in the sunlight."
        },
        {
            "word": "Rug",
            "imagePath": "./assets/images/vocabulary/household-items/rug.png",
            "exampleSentence": "The rug made the living room feel cozy."
        },
        {
            "word": "Mirror",
            "imagePath": "./assets/images/vocabulary/household-items/mirror.png",
            "exampleSentence": "She checked her reflection in the mirror."
        },
        {
            "word": "Blanket",
            "imagePath": "./assets/images/vocabulary/household-items/blanket.png",
            "exampleSentence": "He wrapped himself in a warm blanket."
        },
        {
            "word": "Clock",
            "imagePath": "./assets/images/vocabulary/household-items/clock.png",
            "exampleSentence": "The clock on the wall struck midnight."
        },
        {
            "word": "Alarm clock",
            "imagePath": "./assets/images/vocabulary/household-items/alarm_clock.png",
            "exampleSentence": "His alarm clock woke him up at 6 AM."
        },
        {
            "word": "Laundry Basket",
            "imagePath": "./assets/images/vocabulary/household-items/laundry_basket.png",
            "exampleSentence": "She put her dirty clothes in the laundry basket."
        },
        {
            "word": "Vacuum Cleaner",
            "imagePath": "./assets/images/vocabulary/household-items/vacuum_cleaner.png",
            "exampleSentence": "He used the vacuum cleaner to clean the carpet."
        },
        {
            "word": "Broom",
            "imagePath": "./assets/images/vocabulary/household-items/broom.png",
            "exampleSentence": "She swept the floor with a broom."
        },
        {
            "word": "Trash Can",
            "imagePath": "./assets/images/vocabulary/household-items/trash_can.png",
            "exampleSentence": "He threw the wrappers in the trash can."
        },
        {
            "word": "Tissue box",
            "imagePath": "./assets/images/vocabulary/household-items/tissue_box.png",
            "exampleSentence": "She grabbed a tissue from the tissue box."
        },
        {
            "word": "Remote control",
            "imagePath": "./assets/images/vocabulary/household-items/remote_control.png",
            "exampleSentence": "He used the remote control to change the channel."
        },
        {
            "word": "Binder clip",
            "imagePath": "./assets/images/vocabulary/household-items/binder_clip.png",
            "exampleSentence": "She used a binder clip to hold the papers together."
        },
        {
            "word": "Tape dispenser",
            "imagePath": "./assets/images/vocabulary/household-items/tape_dispenser.png",
            "exampleSentence": "He pulled a piece of tape from the tape dispenser."
        },
        {
            "word": "Stapler",
            "imagePath": "./assets/images/vocabulary/household-items/stapler.png",
            "exampleSentence": "She stapled the pages together using a stapler."
        },
        {
            "word": "Scissors",
            "imagePath": "./assets/images/vocabulary/household-items/scissors.png",
            "exampleSentence": "He cut the paper with a pair of scissors."
        },
        {
            "word": "Stationery",
            "imagePath": "./assets/images/vocabulary/household-items/stationery.png",
            "exampleSentence": "She bought some stationery for school."
        },
        {
            "word": "Calculator",
            "imagePath": "./assets/images/vocabulary/household-items/calculator.png",
            "exampleSentence": "He used a calculator to solve the math problem."
        },
        {
            "word": "Flashlight",
            "imagePath": "./assets/images/vocabulary/household-items/flashlight.png",
            "exampleSentence": "She used a flashlight during the power outage."
        },
        {
            "word": "Screwdriver",
            "imagePath": "./assets/images/vocabulary/household-items/screwdriver.png",
            "exampleSentence": "He fixed the chair with a screwdriver."
        },
        {
            "word": "Hammer",
            "imagePath": "./assets/images/vocabulary/household-items/hammer.png",
            "exampleSentence": "He used a hammer to drive the nail into the wall."
        },
        {
            "word": "Wrench",
            "imagePath": "./assets/images/vocabulary/household-items/wrench.png",
            "exampleSentence": "He tightened the bolt using a wrench."
        },
        {
            "word": "Pliers",
            "imagePath": "./assets/images/vocabulary/household-items/pliers.png",
            "exampleSentence": "She gripped the wire with pliers."
        },
        {
            "word": "Ladder",
            "imagePath": "./assets/images/vocabulary/household-items/ladder.png",
            "exampleSentence": "He climbed the ladder to reach the top shelf."
        },
        {
            "word": "Hair dryer",
            "imagePath": "./assets/images/vocabulary/household-items/hair_dryer.png",
            "exampleSentence": "She used a hair dryer to dry her hair quickly."
        },
        {
            "word": "Basket",
            "imagePath": "./assets/images/vocabulary/household-items/basket.png",
            "exampleSentence": "She placed the fresh fruits in a basket."
        },
        {
            "word": "Umbrella",
            "imagePath": "./assets/images/vocabulary/household-items/umbrella.png",
            "exampleSentence": "He took an umbrella because it was raining."
        },
        {
            "word": "Table Fan",
            "imagePath": "./assets/images/vocabulary/household-items/table_fan.png",
            "exampleSentence": "The table fan kept the room cool."
        },
        {
            "word": "Teapot",
            "imagePath": "./assets/images/vocabulary/household-items/teapot.png",
            "exampleSentence": "She poured hot tea from the teapot."
        },
        {
            "word": "Raincoat",
            "imagePath": "./assets/images/vocabulary/household-items/raincoat.png",
            "exampleSentence": "He wore a raincoat to stay dry in the rain."
        },
        {
            "word": "Radio",
            "imagePath": "./assets/images/vocabulary/household-items/radio.png",
            "exampleSentence": "He listened to the news on the radio."
        },
        {
            "word": "Pestle",
            "imagePath": "./assets/images/vocabulary/household-items/pestle.png",
            "exampleSentence": "She ground the spices with a pestle and mortar."
        },
        {
            "word": "Wardrobe",
            "imagePath": "./assets/images/vocabulary/household-items/wardrobe.png",
            "exampleSentence": "She arranged her clothes in the wardrobe."
        },
        {
            "word": "Desk",
            "imagePath": "./assets/images/vocabulary/household-items/desk.png",
            "exampleSentence": "He placed his laptop on the desk."
        },
        {
            "word": "Stool",
            "imagePath": "./assets/images/vocabulary/household-items/stool.png",
            "exampleSentence": "He sat on a stool at the counter."
        },
        {
            "word": "Cabinet",
            "imagePath": "./assets/images/vocabulary/household-items/cabinet.png",
            "exampleSentence": "She stored dishes in the kitchen cabinet."
        },
        {
            "word": "Pillow",
            "imagePath": "./assets/images/vocabulary/household-items/pillow.png",
            "exampleSentence": "She rested her head on a soft pillow."
        },
        {
            "word": "Towel",
            "imagePath": "./assets/images/vocabulary/household-items/towel.png",
            "exampleSentence": "He dried his hands with a clean towel."
        },
        {
            "word": "Clock",
            "imagePath": "./assets/images/vocabulary/household-items/clock.png",
            "exampleSentence": "The clock on the wall struck noon."
        },
        {
            "word": "Carpet",
            "imagePath": "./assets/images/vocabulary/household-items/carpet.png",
            "exampleSentence": "The carpet made the room feel cozy."
        },
        {
            "word": "Hanger",
            "imagePath": "./assets/images/vocabulary/household-items/hanger.png",
            "exampleSentence": "She hung her dress on a hanger."
        },
        {
            "word": "Iron",
            "imagePath": "./assets/images/vocabulary/household-items/iron.png",
            "exampleSentence": "He used an iron to remove wrinkles."
        },
        {
            "word": "Mop",
            "imagePath": "./assets/images/vocabulary/household-items/mop.png",
            "exampleSentence": "He cleaned the floor with a mop."
        },
        {
            "word": "Bucket",
            "imagePath": "./assets/images/vocabulary/household-items/bucket.png",
            "exampleSentence": "She filled the bucket with water."
        },
        {
            "word": "Toothbrush",
            "imagePath": "./assets/images/vocabulary/household-items/toothbrush.png",
            "exampleSentence": "He brushed his teeth with a toothbrush."
        },
        {
            "word": "Toothpaste",
            "imagePath": "./assets/images/vocabulary/household-items/toothpaste.png",
            "exampleSentence": "She squeezed some toothpaste onto her toothbrush."
        },
        {
            "word": "Razor",
            "imagePath": "./assets/images/vocabulary/household-items/razor.png",
            "exampleSentence": "He shaved his beard with a razor."
        },
        {
            "word": "Shampoo",
            "imagePath": "./assets/images/vocabulary/household-items/shampoo.png",
            "exampleSentence": "She washed her hair with shampoo."
        },
        {
            "word": "Napkins",
            "imagePath": "./assets/images/vocabulary/household-items/napkins.png",
            "exampleSentence": "Please pass the napkins to the guests at the table."
        },
        {
            "word": "Blender",
            "imagePath": "./assets/images/vocabulary/household-items/blender.png",
            "exampleSentence": "She used the blender to make a smoothie."
        },
        {
            "word": "Kettle",
            "imagePath": "./assets/images/vocabulary/household-items/kettle.png",
            "exampleSentence": "She filled the kettle with water to make tea."
        },
        {
            "word": "Vase",
            "imagePath": "./assets/images/vocabulary/household-items/vase.png",
            "exampleSentence": "The vase held a bouquet of fresh flowers."
        },
        {
            "word": "First Aid Kit",
            "imagePath": "./assets/images/vocabulary/household-items/firstaidkit.png",
            "exampleSentence": "The first aid kit was kept in the bathroom for emergencies."
        }
    ],
    "recommends": [
        {
            "image": "./assets/images/thumbnail/fruit-names.png",
            "title": "Fruits Vocabulary – List of Fruit Names in English",
            "url": "https://www.englishskillsjourney.com/vocabulary.html?category=fruits"
        },
        {
            "image": "./assets/images/thumbnail/household-items.png",
            "title": "Household item names in English with pictures",
            "url": "https://www.englishskillsjourney.com/vocabulary.html?category=household-items"
        },
        {
            "image": "./assets/images/thumbnail/transport-names.png",
            "title": "Common Transport Names in English with Pictures",
            "url": "https://www.englishskillsjourney.com/vocabulary.html?category=transport-names"
        }
    ]
}